djinit/__init__.py
djinit/cli.py
djinit/generator.py
djinit/commands/__init__.py
djinit/commands/handler.py
djinit/core/__init__.py
djinit/core/config.py
djinit/core/types.py
djinit/services/__init__.py
djinit/services/app.py
djinit/services/files.py
djinit/services/project.py
djinit/services/templates.py
djinit/templates/components/admin.j2
djinit/templates/components/api_readme.j2
djinit/templates/components/apps.j2
djinit/templates/components/migrations_init.j2
djinit/templates/components/models.j2
djinit/templates/components/models_readme.j2
djinit/templates/components/routes.j2
djinit/templates/components/serializers.j2
djinit/templates/components/tests.j2
djinit/templates/components/urls.j2
djinit/templates/components/views.j2
djinit/templates/config/asgi.j2
djinit/templates/config/wsgi.j2
djinit/templates/config/settings/base.j2
djinit/templates/config/settings/development.j2
djinit/templates/config/settings/production.j2
djinit/templates/config/urls/base.j2
djinit/templates/config/urls/with_api.j2
djinit/templates/config/urls/with_apps.j2
djinit/templates/presets/predefined/api/urls.j2
djinit/templates/presets/predefined/api/v1/urls.j2
djinit/templates/presets/predefined/apps/generic/models.j2
djinit/templates/presets/predefined/apps/generic/serializers.j2
djinit/templates/presets/predefined/apps/generic/services.j2
djinit/templates/presets/predefined/apps/generic/tests.j2
djinit/templates/presets/predefined/apps/generic/urls.j2
djinit/templates/presets/predefined/apps/generic/views.j2
djinit/templates/presets/predefined/apps/users/models.j2
djinit/templates/presets/predefined/apps/users/serializers.j2
djinit/templates/presets/predefined/apps/users/services.j2
djinit/templates/presets/predefined/apps/users/tests.j2
djinit/templates/presets/predefined/apps/users/urls.j2
djinit/templates/presets/predefined/apps/users/views.j2
djinit/templates/presets/predefined/core/exceptions.j2
djinit/templates/presets/predefined/core/middleware/request_logger.j2
djinitx-0.3.3.dist-info/METADATA
djinitx-0.3.3.dist-info/WHEEL
djinitx-0.3.3.dist-info/entry_points.txt
djinitx-0.3.3.dist-info/licenses/LICENSE
djinitx-0.3.3.dist-info/RECORD
