Metadata-Version: 2.4
Name: djinitx
Version: 0.3.3
Summary: A CLI tool to setup Django project
Project-URL: Homepage, https://github.com/S4NKALP/djinit
Author-email: Sankalp Tharu <sankalptharu50028@gmail.com>
License: MIT
License-File: LICENSE
Keywords: cli,dj,django,django project,django starter,django-init,djinit,djinitx,project
Classifier: Environment :: Web Environment
Classifier: Framework :: Django
Classifier: Framework :: Django :: 4.2
Classifier: Framework :: Django :: 5.1
Classifier: Framework :: Django :: 5.2
Classifier: Intended Audience :: Developers
Classifier: License :: OSI Approved :: MIT License
Classifier: Operating System :: OS Independent
Classifier: Programming Language :: Python
Classifier: Programming Language :: Python :: 3
Classifier: Programming Language :: Python :: 3.10
Classifier: Programming Language :: Python :: 3.11
Classifier: Programming Language :: Python :: 3.12
Classifier: Programming Language :: Python :: 3.13
Classifier: Topic :: Internet :: WWW/HTTP
Classifier: Topic :: Internet :: WWW/HTTP :: Dynamic Content
Classifier: Topic :: Software Development :: Code Generators
Classifier: Topic :: Software Development :: Libraries :: Python Modules
Requires-Python: >=3.10
Requires-Dist: jinja2>=3.1.0
Requires-Dist: questionary>=2.0.1
Requires-Dist: rich>=14.2.0
